dunning_cash_flow/__init__.py
dunning_cash_flow/dunning_cash_flow.py
dunning_cash_flow/dunning_cash_flow_unittest.py
dunning_cash_flow-1.0.0.dist-info/LICENSE
dunning_cash_flow-1.0.0.dist-info/METADATA
dunning_cash_flow-1.0.0.dist-info/WHEEL
dunning_cash_flow-1.0.0.dist-info/top_level.txt
dunning_cash_flow-1.0.0.dist-info/RECORD
