Metadata-Version: 2.1
Name: dunning-cash-flow
Version: 1.0.0
Summary: Dunning cash flow is wrapper for Twikey REST APIs : Automatic payments for recurring customers
Home-page: https://bitbucket.org/altf1be/dunning-cash-flow.git
Author: Abdelkrim Boujraf
Author-email: abo+dunning_cash_flow_pkg@alt-f1.be
License: European Union Public Licence 1.2 (EUPL 1.2)
Project-URL: Bug Reports, https://bitbucket.org/altf1be/dunning-cash-flow/issues?status=new&status=open
Project-URL: Company behind the library, http://www.alt-f1.be
Project-URL: Source, https://bitbucket.org/altf1be/dunning-cash-flow
Keywords: library,dunning_service,alt-f1.be
Platform: UNKNOWN
Classifier: Development Status :: 5 - Production/Stable
Classifier: Intended Audience :: Developers
Classifier: License :: OSI Approved :: European Union Public Licence 1.2 (EUPL 1.2)
Classifier: Operating System :: OS Independent
Classifier: Programming Language :: Python :: 3.7
Classifier: Topic :: Software Development :: Libraries :: Python Modules
Requires-Python: >=3.5
Requires-Dist: requests
Requires-Dist: pandas
Requires-Dist: country-list
